CHANGES
MANIFEST.in
README.md
setup.py
jira_analysis/__init__.py
jira_analysis/manage.py
jira_analysis/settings.py
jira_analysis/wsgi.py
jira_analysis/analysis/__init__.py
jira_analysis/analysis/admin.py
jira_analysis/analysis/fields.py
jira_analysis/analysis/models.py
jira_analysis/analysis/urls.py
jira_analysis/analysis/views.py
jira_analysis/analysis/templates/base.html
jira_analysis/analysis/templates/help.html
jira_analysis/analysis/templates/infographics.html
jira_analysis/analysis/templates/loops.html
jira_analysis/analysis/templates/main.html
jira_analysis/analysis/templates/statuses.html
jira_analysis/analysis/templatetags/__init__.py
jira_analysis/analysis/templatetags/extra_tags.py
jira_analysis/dataminer/__init__.py
jira_analysis/dataminer/admin.py
jira_analysis/dataminer/models.py
jira_analysis/dataminer/tests.py
jira_analysis/dataminer/views.py
jira_analysis/static/css/bootstrap-theme.css
jira_analysis/static/css/bootstrap-theme.min.css
jira_analysis/static/css/bootstrap.css
jira_analysis/static/css/bootstrap.min.css
jira_analysis/static/css/jira_analysis.css
jira_analysis/static/fonts/glyphicons-halflings-regular.eot
jira_analysis/static/fonts/glyphicons-halflings-regular.svg
jira_analysis/static/fonts/glyphicons-halflings-regular.ttf
jira_analysis/static/fonts/glyphicons-halflings-regular.woff
jira_analysis/static/ico/favicon.ico
jira_analysis/static/js/bootstrap.js
jira_analysis/static/js/bootstrap.min.js
jira_analysis/static/js/highcharts-more.js
jira_analysis/static/js/highcharts.js
jira_analysis/static/js/highcharts.src.js
jira_analysis/static/js/adapters/mootools-adapter.js
jira_analysis/static/js/adapters/mootools-adapter.src.js
jira_analysis/static/js/adapters/prototype-adapter.js
jira_analysis/static/js/adapters/prototype-adapter.src.js
jira_analysis/static/js/modules/canvas-tools.js
jira_analysis/static/js/modules/canvas-tools.src.js
jira_analysis/static/js/modules/data.js
jira_analysis/static/js/modules/data.src.js
python_jira_analysis.egg-info/PKG-INFO
python_jira_analysis.egg-info/SOURCES.txt
python_jira_analysis.egg-info/dependency_links.txt
python_jira_analysis.egg-info/not-zip-safe
python_jira_analysis.egg-info/requires.txt
python_jira_analysis.egg-info/top_level.txt
