Metadata-Version: 1.1
Name: python-jira-analysis
Version: 0.0.2
Summary: JIRA dashboard tools for Kanban
Home-page: ssh://hg@bitbucket.org/fikander/python-jira-analysis
Author: Shazam
Author-email: tomasz.kustrzynski@shazam.com
License: Apache License 2.0
Keywords: jira kanban
Platform: UNKNOWN
Classifier: Programming Language :: Python
Classifier: Framework :: Django
Classifier: Development Status :: 2 - Pre-Alpha
Classifier: Intended Audience :: Developers
Classifier: License :: OSI Approved :: Apache Software License
Classifier: Topic :: Software Development :: Libraries :: Python Modules
Classifier: Topic :: Internet
